crystal4D/__init__.py
crystal4D/version.py
crystal4D/augmentation/__init__.py
crystal4D/augmentation/augmentation.py
crystal4D/augmentation/interpolate.py
crystal4D/layers/__init__.py
crystal4D/layers/convQuad.py
crystal4D/layers/convSpectral.py
crystal4D/layers/multiTaskLayer.py
crystal4D/layers/poolSpectral.py
crystal4D/models/__init__.py
crystal4D/models/complexSpecPoolUnet.py
crystal4D/models/complexUnet.py
crystal4D/models/complexUnetMultiHead.py
crystal4D/models/spectralPoolDenseNet.py
crystal4D/models/spectralPoolUnet.py
crystal4D/models/spectralUnet.py
crystal4D/models/unet.py
crystal4D/utils/__init__.py
crystal4D/utils/aug_utils.py
crystal4D/utils/conv_utils.py
crystal4D/utils/data_utils.py
crystal4D/utils/gp_utils.py
crystal4D/utils/loss_utils.py
crystal4D/utils/py4dstem_utils.py
crystal4D/utils/utils.py
crystal4D/visualize/__init__.py
crystal4D/visualize/visualize.py
crystal4D-0.1.7.dist-info/METADATA
crystal4D-0.1.7.dist-info/WHEEL
crystal4D-0.1.7.dist-info/top_level.txt
crystal4D-0.1.7.dist-info/RECORD
