Metadata-Version: 2.1
Name: crystal4D
Version: 0.1.7
Summary: Deep learning useful information from diffraction images
Home-page: UNKNOWN
Author: Joydeep Munshi
License: UNKNOWN
Keywords: STEM 4DSTEM AI/ML
Platform: UNKNOWN
Classifier: Programming Language :: Python :: 3
Classifier: License :: OSI Approved :: MIT License
Classifier: Operating System :: OS Independent
Requires-Python: >=3.6
Requires-Dist: numpy (>=1.19)
Requires-Dist: matplotlib (>=3.4.2)
